xover/__init__.py
xover/inversion.py
xover/meta.py
xover-2.0.0.dist-info/licenses/LICENSE
xover-2.0.0.dist-info/METADATA
xover-2.0.0.dist-info/WHEEL
xover-2.0.0.dist-info/top_level.txt
xover-2.0.0.dist-info/RECORD
